state_machine/__init__.py
state_machine/models/__init__.py
state_machine/orm/__init__.py
state_machine/orm/base.py
state_machine/orm/mongoengine.py
state_machine/orm/sqlalchemy.py
state_machine-0.2.10.dist-info/DESCRIPTION.rst
state_machine-0.2.10.dist-info/METADATA
state_machine-0.2.10.dist-info/RECORD
state_machine-0.2.10.dist-info/WHEEL
state_machine-0.2.10.dist-info/metadata.json
state_machine-0.2.10.dist-info/top_level.txt
