Metadata-Version: 2.0
Name: state-machine
Version: 0.2.10
Summary: Python State Machines for Humans
Home-page: http://github.com/jtushman/state_machine
Author: Jonathan Tushman
Author-email: jonathan@gmail.com
License: MIT
Platform: UNKNOWN
Classifier: Intended Audience :: Developers
Classifier: License :: OSI Approved :: MIT License
Classifier: Programming Language :: Python :: 2.7
Classifier: Programming Language :: Python :: 3
